socketio_handler/__init__.py
socketio_handler/app.py
socketio_handler/handler.py
socketio_handler/socket_registry.py
socketio_handler/types.py
fastapi_socketio_handler-0.4.0.dist-info/METADATA
fastapi_socketio_handler-0.4.0.dist-info/WHEEL
fastapi_socketio_handler-0.4.0.dist-info/licenses/LICENSE
fastapi_socketio_handler-0.4.0.dist-info/RECORD
