Metadata-Version: 2.4
Name: fastapi-socketio-handler
Version: 0.4.0
Summary: Socket.IO wrapper for FastApi applications
License: MIT
License-File: LICENSE
Keywords: socketio,asyncio,websockets,python-socketio,asyncio-socketio,websockets-handler,fastapi
Author: Nazarii
Author-email: bandirom@ukr.net
Requires-Python: >=3.9
Classifier: Framework :: FastAPI
Classifier: License :: OSI Approved :: MIT License
Classifier: Operating System :: OS Independent
Classifier: Programming Language :: Python
Classifier: Programming Language :: Python :: 3
Classifier: Programming Language :: Python :: 3.9
Classifier: Programming Language :: Python :: 3.10
Classifier: Programming Language :: Python :: 3.11
Classifier: Programming Language :: Python :: 3.12
Classifier: Programming Language :: Python :: 3.13
Classifier: Programming Language :: Python :: 3.14
Classifier: Topic :: Communications :: Chat
Classifier: Topic :: Internet
Classifier: Topic :: Internet :: WWW/HTTP
Classifier: Topic :: Internet :: WWW/HTTP :: Dynamic Content
Classifier: Topic :: Software Development :: Libraries :: Application Frameworks
Classifier: Topic :: Software Development :: Libraries :: Python Modules
Requires-Dist: fastapi
Requires-Dist: python-socketio[asyncio] (>=5.13.0,<6.0.0)
Project-URL: changelog, https://github.com/bandirom/fastapi-socketio-handler/blob/main/CHANGELOG.md
Project-URL: homepage, https://github.com/bandirom/fastapi-socketio-handler
Project-URL: issues, https://github.com/bandirom/fastapi-socketio-handler/issues
Project-URL: repository, https://github.com/bandirom/fastapi-socketio-handler
